{
  "username": "ka3xl6cd",
  "password": "by0jknuv8bwd",
  "withdrawPassword": "763591",
  "fullname": "VO HUU DUC MINH BAO",
  "email": "dl2qiz@gmail.com",
  "phone": "0792566015",
  "bank": {
    "name": "MSB",
    "branch": "Thành phố Hồ Chí Minh",
    "accountNumber": "96959403171",
    "accountHolder": "VO HUU DUC MINH BAO"
  },
  "registeredAt": "2025-12-29T09:31:17.716Z",
  "firstSite": "MB66",
  "sites": [
    "SHBET",
    "NEW88",
    "MB66",
    "789BET"
  ],
  "status": "active",
  "category": "okvip",
  "tool": "vip-tool"
}